mrQA/__compliance__.py
mrQA/__init__.py
mrQA/_version.py
mrQA/cli.py
mrQA/common.py
mrQA/config.py
mrQA/formatter.py
mrQA/layout.html
mrQA/monitor.py
mrQA/parallel_utils.py
mrQA/project.py
mrQA/run_merge.py
mrQA/run_parallel.py
mrQA/run_subset.py
mrQA/utils.py
mrQA/tests/__init__.py
mrQA/tests/config.py
mrQA/tests/conftest.py
mrQA/tests/test_compliance.py
mrQA/tests/test_monitor.py
mrQA/tests/test_parallel.py
mrQA/tests/unit_tests.py
mrQA/tests/utils.py
mrQA-0.2.4.dist-info/AUTHORS.rst
mrQA-0.2.4.dist-info/LICENSE
mrQA-0.2.4.dist-info/METADATA
mrQA-0.2.4.dist-info/WHEEL
mrQA-0.2.4.dist-info/entry_points.txt
mrQA-0.2.4.dist-info/top_level.txt
mrQA-0.2.4.dist-info/RECORD
