Metadata-Version: 2.1
Name: mrQA
Version: 0.2.4
Summary: mrQA suite of tools offering automatic evaluation of protocol compliance
Home-page: https://github.com/Open-Minds-Lab/mrQA
Author: Pradeep Raamana
Author-email: raamana@gmail.com
License: Apache Software License 2.0
Keywords: mrQA
Platform: UNKNOWN
Classifier: Development Status :: 2 - Pre-Alpha
Classifier: Intended Audience :: Developers
Classifier: License :: OSI Approved :: Apache Software License
Classifier: Natural Language :: English
Classifier: Programming Language :: Python :: 3
Classifier: Programming Language :: Python :: 3.6
Classifier: Programming Language :: Python :: 3.7
Classifier: Programming Language :: Python :: 3.8
Requires-Python: >=3.6
License-File: LICENSE
License-File: AUTHORS.rst
Requires-Dist: mrdataset
Requires-Dist: pydicom
Requires-Dist: nibabel
Requires-Dist: dictdiffer
Requires-Dist: jinja2 (>=3.0.3)
